sfjson/__init__.py
sfjson/util.py
sfjson-2.0.1.dist-info/METADATA
sfjson-2.0.1.dist-info/WHEEL
sfjson-2.0.1.dist-info/top_level.txt
sfjson-2.0.1.dist-info/RECORD
