Metadata-Version: 2.1
Name: sfjson
Version: 2.0.1
Summary: sfjson
Home-page: https://github.com/ClearVoice/sfjson-python
Author: Jeff Nappi
Author-email: jeff@clearvoice.com
License: MIT
Platform: UNKNOWN
Classifier: Intended Audience :: Developers
Classifier: License :: OSI Approved :: MIT License
Classifier: Programming Language :: Python
Classifier: Topic :: Software Development :: Libraries :: Python Modules
Requires-Dist: sleekxmpp
Requires-Dist: tlslite
Requires-Dist: pyasn1
Requires-Dist: pyasn1-modules
Requires-Dist: python-dateutil
